fixture/__init__-4.py
fixture/fixture.py
league/__init__-3.py
league/league.py
player/__init__-2.py
player/player.py
team/__init__-1.py
team/team.py
league_maker-1.0.0.dist-info/METADATA
league_maker-1.0.0.dist-info/WHEEL
league_maker-1.0.0.dist-info/top_level.txt
league_maker-1.0.0.dist-info/RECORD
