Metadata-Version: 2.1
Name: league-maker
Version: 1.0.0
Summary: create new league, team, player and fixtures with ease
Home-page: https://github.com/king-tomi/league
Author: Ayodabo Tomisin
License: MIT
Platform: UNKNOWN
Classifier: License :: OSI Approved :: MIT License
Classifier: Programming Language :: Python :: 3
Classifier: Programming Language :: Python :: 3.9
Requires-Dist: pandas
